[
  {
    "id": 1,
    "name": "Evotech Pro España",
    "codes": [
      {"info": "wordpress"}
    ],
    "type": "ecommerce",
    "link": "https://evotechpro.es/",
    "logo": "https://raw.githubusercontent.com/DR-Frontend/portfolio/e009b790ac782136255652a9af1a566acb74f942/src/assets/svg/web_evotech.svg",
    "seo": "David Romero Diseñador Frontend"
  },
  {
    "id": 2,
    "name": "Geekode Design",
    "codes": [
      {"info": "html"},
      {"info": "css"}
    ],
    "type": "single-page",
    "link": "https://geekode-design.web.app/",
    "logo": "https://raw.githubusercontent.com/DR-Frontend/portfolio/e009b790ac782136255652a9af1a566acb74f942/src/assets/svg/web_geekode.svg",
    "seo": "David Romero Diseñador Frontend"
  },
  {
    "id": 4,
    "name": "Dicard",
    "codes": [
      {"info": "html"},
      {"info": "css"}
    ],
    "type": "single-page",
    "link": "https://dr-frontend.github.io/dicard/",
    "logo": "https://raw.githubusercontent.com/DR-Frontend/portfolio/e009b790ac782136255652a9af1a566acb74f942/src/assets/svg/web_dicard.svg",
    "seo": "David Romero Diseñador Frontend"
  },
  {
    "id": 5,
    "name": "Enal Anuncios",
    "codes": [
      {"info": "html"},
      {"info": "css"}
    ],
    "type": "single-page",
    "link": "https://dr-frontend.github.io/enal/",
    "logo": "https://raw.githubusercontent.com/DR-Frontend/portfolio/e009b790ac782136255652a9af1a566acb74f942/src/assets/svg/web_enal.svg",
    "seo": "David Romero Diseñador Frontend"
  },
  {
    "id": 6,
    "name": "Cadpa Armonizadores",
    "codes": [
      {"info": "html"},
      {"info": "css"}
    ],
    "type": "single-page",
    "link": "https://cadpa-armonizadores.web.app/",
    "logo": "https://raw.githubusercontent.com/DR-Frontend/portfolio/e009b790ac782136255652a9af1a566acb74f942/src/assets/svg/web_cadpa.svg",
    "seo": "David Romero Diseñador Frontend"
  },
  {
    "id": 7,
    "name": "Tamales La Madrina Nancy",
    "codes": [
      {"info": "html"},
      {"info": "css"},
      {"info": "react"}
    ],
    "type": "single-page",
    "link": "https://dr-frontend.github.io/tamales-nancy/",
    "logo": "https://raw.githubusercontent.com/DR-Frontend/portfolio/e009b790ac782136255652a9af1a566acb74f942/src/assets/svg/web_tamales.svg",
    "seo": "David Romero Diseñador Frontend"
  },
  {
    "id": 8,
    "name": "MH 20th Anniversary",
    "codes": [
      {"info": "html"},
      {"info": "css"},
      {"info": "react"},
      {"info": "práctica"}
    ],
    "type": "landing-page",
    "link": "https://dr-frontend.github.io/mh-landing-page/",
    "logo": "https://raw.githubusercontent.com/DR-Frontend/portfolio/master/src/assets/svg/web_mh.svg",
    "seo": "David Romero Diseñador Frontend"
  }
]